{"chunk_definitions":[{"row":21,"row_count":1,"visible":true,"expansion_state":0,"options":{"engine":"r","label":"unnamed-chunk-37","dev":"png"},"document_id":"59FC34E3","chunk_id":"cz9m0r8c01l9t","chunk_label":"unnamed-chunk-1"},{"row":32,"row_count":1,"visible":true,"expansion_state":0,"options":{"engine":"r","label":"unnamed-chunk-38","dev":"png"},"document_id":"59FC34E3","chunk_id":"c5l9sity37szl","chunk_label":"unnamed-chunk-2"},{"row":39,"row_count":1,"visible":true,"expansion_state":0,"options":{"engine":"r","label":"unnamed-chunk-39","dev":"png"},"document_id":"59FC34E3","chunk_id":"c9oal8su2e96f","chunk_label":"unnamed-chunk-3"},{"row":46,"row_count":1,"visible":true,"expansion_state":0,"options":{"engine":"r","label":"unnamed-chunk-40","dev":"png"},"document_id":"59FC34E3","chunk_id":"cmo54p5vlcgzc","chunk_label":"unnamed-chunk-4"},{"row":53,"row_count":1,"visible":true,"expansion_state":0,"options":{"engine":"r","label":"unnamed-chunk-41","dev":"png"},"document_id":"59FC34E3","chunk_id":"cbs0srd6jndjd","chunk_label":"unnamed-chunk-5"},{"row":65,"row_count":1,"visible":true,"expansion_state":0,"options":{"engine":"r","label":"unnamed-chunk-42","dev":"png"},"document_id":"59FC34E3","chunk_id":"ca2gkr6qjo5po","chunk_label":"unnamed-chunk-6"},{"row":77,"row_count":1,"visible":true,"expansion_state":0,"options":{"engine":"r","label":"unnamed-chunk-43","dev":"png"},"document_id":"59FC34E3","chunk_id":"cenn9l7vps6ge","chunk_label":"unnamed-chunk-7"},{"row":85,"row_count":1,"visible":true,"expansion_state":0,"options":{"engine":"r","label":"unnamed-chunk-44","dev":"png"},"document_id":"59FC34E3","chunk_id":"caq2cgz34bd3f","chunk_label":"unnamed-chunk-8"},{"row":92,"row_count":1,"visible":true,"expansion_state":0,"options":{"engine":"r","label":"unnamed-chunk-45","dev":"png"},"document_id":"59FC34E3","chunk_id":"cvemegs3cjk39","chunk_label":"unnamed-chunk-9"},{"row":101,"row_count":1,"visible":true,"expansion_state":0,"options":{"engine":"r","label":"unnamed-chunk-46","dev":"png"},"document_id":"59FC34E3","chunk_id":"c385bli7xpf6z","chunk_label":"unnamed-chunk-10"},{"row":120,"row_count":1,"visible":true,"expansion_state":0,"options":{"engine":"r","label":"unnamed-chunk-47","dev":"png"},"document_id":"59FC34E3","chunk_id":"cninz2t3h8art","chunk_label":"unnamed-chunk-11"},{"row":126,"row_count":1,"visible":true,"expansion_state":0,"options":{"engine":"r","label":"unnamed-chunk-48","dev":"png"},"document_id":"59FC34E3","chunk_id":"c7207zkwii1y3","chunk_label":"unnamed-chunk-12"},{"row":152,"row_count":1,"visible":true,"expansion_state":0,"options":{"engine":"r","label":"unnamed-chunk-49","dev":"png"},"document_id":"59FC34E3","chunk_id":"co36rjr6omsp4","chunk_label":"unnamed-chunk-13"},{"row":161,"row_count":1,"visible":true,"expansion_state":0,"options":{"engine":"r","label":"unnamed-chunk-50","dev":"png"},"document_id":"59FC34E3","chunk_id":"c41uqthk9j5rc","chunk_label":"unnamed-chunk-14"},{"row":165,"row_count":1,"visible":true,"expansion_state":0,"options":{"engine":"r","label":"unnamed-chunk-51","dev":"png"},"document_id":"59FC34E3","chunk_id":"ctbrd2tetbi1x","chunk_label":"unnamed-chunk-15"},{"row":176,"row_count":1,"visible":true,"expansion_state":0,"options":{"engine":"r","label":"unnamed-chunk-52","dev":"png"},"document_id":"59FC34E3","chunk_id":"c0m27nfkprjob","chunk_label":"unnamed-chunk-16"},{"row":186,"row_count":1,"visible":true,"expansion_state":0,"options":{"engine":"r","label":"unnamed-chunk-53","dev":"png"},"document_id":"59FC34E3","chunk_id":"c5bkr44g1u1wa","chunk_label":"unnamed-chunk-17"},{"row":192,"row_count":1,"visible":true,"expansion_state":0,"options":{"engine":"r","label":"unnamed-chunk-54","dev":"png"},"document_id":"59FC34E3","chunk_id":"c0nroopz71ilx","chunk_label":"unnamed-chunk-18"},{"row":196,"row_count":1,"visible":true,"expansion_state":0,"options":{"engine":"r","label":"unnamed-chunk-55","dev":"png"},"document_id":"59FC34E3","chunk_id":"c336clxsxvh2x","chunk_label":"unnamed-chunk-19"},{"row":209,"row_count":1,"visible":true,"expansion_state":0,"options":{"engine":"r","label":"unnamed-chunk-56","dev":"png"},"document_id":"59FC34E3","chunk_id":"csip4u4ov7fl2","chunk_label":"unnamed-chunk-20"},{"row":213,"row_count":1,"visible":true,"expansion_state":0,"options":{"engine":"r","label":"unnamed-chunk-57","dev":"png"},"document_id":"59FC34E3","chunk_id":"cpl5btbppn2ie","chunk_label":"unnamed-chunk-21"},{"row":217,"row_count":1,"visible":true,"expansion_state":0,"options":{"engine":"r","label":"unnamed-chunk-58","dev":"png"},"document_id":"59FC34E3","chunk_id":"c337wl2chrtyv","chunk_label":"unnamed-chunk-22"}],"doc_write_time":1760984720}